brainFuckInterpreter/__init__.py
brainFuckInterpreter/fuck.py
BrainpyFuck-0.0.4.dist-info/LICENSE
BrainpyFuck-0.0.4.dist-info/METADATA
BrainpyFuck-0.0.4.dist-info/WHEEL
BrainpyFuck-0.0.4.dist-info/top_level.txt
BrainpyFuck-0.0.4.dist-info/RECORD
