Metadata-Version: 2.1
Name: BrainpyFuck
Version: 0.0.4
Summary: A small brainfuck interpreter for python, including prettyprint inside
Home-page: https://github.com/Forever-CodingNoob/BrainFuck
Author: ForeverCdgNoob
Author-email: johnnylin6526@gmail.com
License: UNKNOWN
Platform: UNKNOWN
Classifier: Programming Language :: Python :: 3
Classifier: License :: OSI Approved :: MIT License
Classifier: Operating System :: OS Independent
Requires-Python: >=3.6
